mjsqltool/__init__.py
mjsqltool/clean.py
mjsqltool/connectdb.py
mjsqltool/package.py
mjsqltool/pgsqltool.py
mjsqltool-2.1.2.dist-info/LICENSE
mjsqltool-2.1.2.dist-info/METADATA
mjsqltool-2.1.2.dist-info/WHEEL
mjsqltool-2.1.2.dist-info/top_level.txt
mjsqltool-2.1.2.dist-info/RECORD
