Metadata-Version: 2.1
Name: mjsqltool
Version: 2.1.2
Summary: 数据库工具
Home-page: https://gitee.com/manjim/sqltool
Author: manji
Author-email: pnsm@qq.com
Classifier: Programming Language :: Python :: 3
Classifier: License :: OSI Approved :: MIT License
Classifier: Operating System :: OS Independent
Requires-Python: >=3
License-File: LICENSE
Requires-Dist: sqlalchemy
Requires-Dist: pandas
Requires-Dist: numpy
Requires-Dist: pymysql
Requires-Dist: psycopg2
